datajunction/__about__.py
datajunction/__init__.py
datajunction/_base.py
datajunction/_internal.py
datajunction/admin.py
datajunction/builder.py
datajunction/cli.py
datajunction/client.py
datajunction/compile.py
datajunction/deployment.py
datajunction/exceptions.py
datajunction/models.py
datajunction/nodes.py
datajunction/tags.py
datajunction/seed/init_system_nodes.py
datajunction/seed/nodes/date.dimension.yaml
datajunction/seed/nodes/dimension_link.dimension.yaml
datajunction/seed/nodes/dj.yaml
datajunction/seed/nodes/is_active.dimension.yaml
datajunction/seed/nodes/materialization.dimension.yaml
datajunction/seed/nodes/node_type.dimension.yaml
datajunction/seed/nodes/node_without_description.metric.yaml
datajunction/seed/nodes/nodes.dimension.yaml
datajunction/seed/nodes/number_of_materializations.metric.yaml
datajunction/seed/nodes/number_of_nodes.metric.yaml
datajunction/seed/nodes/user.dimension.yaml
datajunction-0.0.56.dist-info/METADATA
datajunction-0.0.56.dist-info/WHEEL
datajunction-0.0.56.dist-info/entry_points.txt
datajunction-0.0.56.dist-info/licenses/LICENSE.txt
datajunction-0.0.56.dist-info/RECORD
