Metadata-Version: 2.4
Name: datajunction
Version: 0.0.56
Summary: DataJunction client library for connecting to a DataJunction server
Project-URL: repository, https://github.com/DataJunction/dj
Author-email: DataJunction Authors <yian.shang@gmail.com>
License: MIT
License-File: LICENSE.txt
Classifier: License :: OSI Approved :: MIT License
Classifier: Operating System :: OS Independent
Classifier: Programming Language :: Python :: 3.10
Classifier: Programming Language :: Python :: 3.11
Classifier: Programming Language :: Python :: 3.12
Requires-Python: <4.0,>=3.10
Requires-Dist: alive-progress>=3.1.2
Requires-Dist: httpx>=0.27.0
Requires-Dist: pytest-xdist>=3.5.0
Requires-Dist: pyyaml>=6.0.1
Requires-Dist: requests<3.0.0,>=2.28.2
Requires-Dist: rich>=13.7.0
Provides-Extra: pandas
Requires-Dist: pandas>=2.0.2; extra == 'pandas'
